suitcase/tiff_series/__init__.py
suitcase/tiff_series/_version.py
suitcase/tiff_series/tests/__init__.py
suitcase/tiff_series/tests/conftest.py
suitcase/tiff_series/tests/tests.py
suitcase/tiff_stack/__init__.py
suitcase/tiff_stack/_version.py
suitcase/tiff_stack/tests/__init__.py
suitcase/tiff_stack/tests/conftest.py
suitcase/tiff_stack/tests/tests.py
suitcase_tiff-0.4.0.dist-info/LICENSE
suitcase_tiff-0.4.0.dist-info/METADATA
suitcase_tiff-0.4.0.dist-info/WHEEL
suitcase_tiff-0.4.0.dist-info/entry_points.txt
suitcase_tiff-0.4.0.dist-info/top_level.txt
suitcase_tiff-0.4.0.dist-info/RECORD
