Metadata-Version: 2.1
Name: suitcase-tiff
Version: 0.4.0
Summary: UNKNOWN
Home-page: UNKNOWN
License: BSD (3-clause)
Platform: UNKNOWN
Classifier: Development Status :: 2 - Pre-Alpha
Classifier: Natural Language :: English
Classifier: Programming Language :: Python :: 3.6
License-File: LICENSE
Requires-Dist: event-model (>=1.8.0)
Requires-Dist: suitcase-utils
Requires-Dist: tifffile (!=2019.7.26.2)
